tamagotchi/__init__.py
tamagotchi/storage.py
tamagotchi/tamagotchi.py
tests/__init__.py
tests/test.py
tamagotchi_jeu-0.1.dist-info/METADATA
tamagotchi_jeu-0.1.dist-info/WHEEL
tamagotchi_jeu-0.1.dist-info/top_level.txt
tamagotchi_jeu-0.1.dist-info/RECORD
