Metadata-Version: 2.1
Name: tamagotchi_jeu
Version: 0.1
Summary: Un jeu Tamagotchi en Python
Home-page: https://github.com/toncompte/tamagotchi
Author: Meyer Robin
Author-email: robin.meyer@cpe.fr
License: UNKNOWN
Platform: UNKNOWN
Classifier: Programming Language :: Python :: 3
Classifier: License :: OSI Approved :: MIT License
Classifier: Operating System :: OS Independent
